{
  "slug": "the-ultimate-guide-to-year-round-landscaping-in-chicago-thrive-in-all-four-seasons",
  "title": "The Ultimate Guide to Year-Round Landscaping in Chicago: Thrive in All Four Seasons",
  "intro": "Living in Chicago means experiencing the full, dramatic range of four distinct seasons. From blistering summer heat to bone-chilling winter snow, our landscapes endure a lot. But this challenge is also an opportunity. A well-designed Chicago landscape isn't just about surviving—it's about creating a beautiful, functional outdoor space that offers something special year-round. This guide provides expert advice for homeowners looking to cultivate a resilient and stunning yard that truly thrives in our unique climate.",
  "date": "2025-12-09",
  "content": "<h2>Understanding Chicago's Climate: The Foundation of Success</h2>\n<p>Before you plant a single flower, it's crucial to understand the local environment. Chicago falls primarily within USDA Hardiness Zone 6a, meaning we experience minimum winter temperatures of -10 to -5°F. However, the 'lake effect' from Lake Michigan can create microclimates, moderating temperatures near the shore while sometimes intensifying snowfalls. Successful landscaping in our region means selecting hardy plants that can withstand our cold winters and humid summers, and implementing practices that prepare your yard for these seasonal shifts.</p>\n<h2>Spring Awakening: Preparing Your Landscape for Growth</h2>\n<p>As the snow melts and the ground thaws, it's time to lay the groundwork for a lush season ahead.</p>\n<h2>H3: Critical Cleanup & Soil Preparation</h2>\n<p>Start by clearing away winter debris—fallen branches, matted leaves, and any lingering salt residue from walkways. This is the perfect time to prune dead or damaged branches from trees and shrubs to encourage healthy new growth. Rake your lawn gently to remove thatch. Most importantly, test your soil. Chicago-area soil can be heavy clay; amending it with compost will improve drainage and provide essential nutrients for your plants.</p>\n<h2>H3: Planting for Spring Color & Beyond</h2>\n<p>Introduce early color with cool-weather annuals like pansies and snapdragons. For long-term beauty, plant perennials that are proven winners in our zone, such as Hostas for shady areas, Peonies for spectacular blooms, and Allium for a touch of modern structure. Spring is also an ideal time for planting many new trees and shrubs.</p>\n<h2>Summer Vibrancy: Maintaining a Lush Oasis</h2>\n<p>Chicago summers can be hot and humid, which can stress your plants and lawn. The key to a thriving summer landscape is smart maintenance.</p>\n<h2>H3: Smart Watering and Mulching</h2>\n<p>Water your lawn and garden beds deeply but infrequently, preferably in the early morning to minimize evaporation. This encourages deep root growth, making plants more drought-tolerant. Apply a 2-3 inch layer of high-quality mulch around your plants and trees. Mulch is a landscaper's best friend—it retains soil moisture, suppresses weeds, and regulates soil temperature.</p>\n<h2>H3: Embrace Native, Heat-Tolerant Plants</h2>\n<p>For a truly low-maintenance and resilient garden, incorporate native Illinois plants. Purple Coneflower (Echinacea purpurea), Black-Eyed Susans (Rudbeckia hirta), and Prairie Dropseed (Sporobolus heterolepis) are not only beautiful but are perfectly adapted to our summer heat and local soils, requiring less water and providing vital habitat for pollinators.</p>\n<h2>Autumn Allure: Winding Down and Preparing for Winter</h2>\n<p>Fall is not an end, but a crucial transition. The work you do now directly impacts the health of your landscape next spring.</p>\n<h2>H3: Fall Planting & Lawn Fortification</h2>\n<p>The cool air and warm soil of autumn create the perfect conditions for planting spring-blooming bulbs like tulips and daffodils. It's also the best time to plant new trees and shrubs, giving them a chance to establish roots before winter. Fertilize your lawn one last time to promote strong root development that will help it survive the cold and green up faster in the spring.</p>\n<h2>H3: Winterization and Protection</h2>\n<p>After the first hard frost, cut back spent perennials. Rake up fallen leaves to prevent them from smothering your lawn and creating a haven for pests. Most importantly, if you have an irrigation system, have it professionally blown out to prevent pipes from freezing and bursting over the winter—a costly mistake to avoid.</p>\n<h2>Winter Interest: Beauty in the Quiet Season</h2>\n<p>A Chicago landscape shouldn't look barren for five months. A thoughtful design provides beauty and structure even when covered in snow.</p>\n<h2>H3: Focus on Structure and 'Good Bones'</h2>\n<p>This is where evergreens are invaluable. Varieties like Boxwood, Arborvitae, and Holly provide year-round color and form. Trees with interesting bark, such as River Birch or Paperbark Maple, become living sculptures. Ornamental grasses like Karl Foerster Feather Reed Grass, left standing through the winter, add texture and movement to the frozen landscape.</p>\n<h2>H3: The Role of Hardscaping</h2>\n<p>Well-designed patios, walkways, and retaining walls form the backbone of your landscape. They define spaces and remain visible year-round. A strategically placed fire pit can even extend the use of your outdoor space into the cooler months, offering a cozy gathering spot on a crisp winter evening.</p>\n<h2>Conclusion</h2><p>Creating a breathtaking landscape in Chicago is a year-long endeavor that rewards careful planning and seasonal expertise. By understanding our climate, choosing the right plants, and performing timely maintenance, you can craft an outdoor space that is not only resilient but offers dynamic beauty through every season. It's about working with nature to build a landscape that is a true extension of your home.</p>\n<p><strong>Feeling inspired but overwhelmed? Let the experts handle the hard work. Contact our professional landscaping team today for a consultation. We specialize in designing, building, and maintaining beautiful four-season landscapes for Chicago homeowners.</strong></p>\n"
}